Metadata-Version: 2.1
Name: logging-azure-rest
Version: 1.3.0
Summary: A python threadded logging handler and service extension for Azure Log Workspace OMS REST API.
Home-page: https://github.com/Exelscior/logging-azure-rest
Author: Joshua Logan
Author-email: joshua.logan@exelscior.eu
License: MIT
Keywords: utils
Platform: UNKNOWN
Classifier: Development Status :: 5 - Production/Stable
Classifier: Environment :: Plugins
Classifier: Intended Audience :: Developers
Classifier: License :: OSI Approved :: MIT License
Classifier: Operating System :: OS Independent
Classifier: Natural Language :: English
Classifier: Programming Language :: Python :: 3.7
Classifier: Topic :: Software Development :: Libraries :: Python Modules
Requires-Python: >=3.7
